[
  {
    "area_id": 1,
    "area_name": "目瑙纵歌路商圈",
    "description": "位于盈江县城核心区域，沿目瑙纵歌路分布的主要商业聚集区",
    "mall_codes": [
      "MALL_57FCF283",
      "MALL_BF6C2E37",
      "MALL_CCCA17B7"
    ]
  },
  {
    "area_id": 2,
    "area_name": "永盛路商圈",
    "description": "以永盛路为核心的城市商业中心，包含多个购物中心和商场",
    "mall_codes": [
      "MALL_6951C446",
      "MALL_BA8F9CE2",
      "MALL_DB4EE91B",
      "MALL_12E66DD6"
    ]
  },
  {
    "area_id": 3,
    "area_name": "密回路商圈",
    "description": "位于密回路沿线的商业区域，连接县城主要交通要道",
    "mall_codes": [
      "MALL_3010A1CF"
    ]
  },
  {
    "area_id": 4,
    "area_name": "赏建路商圈",
    "description": "位于县城南部的商业区域，以启宏大商汇为核心",
    "mall_codes": [
      "MALL_F01B964E"
    ]
  },
  {
    "area_id": 5,
    "area_name": "户勐商圈",
    "description": "位于县城北部户勐区域的商业中心",
    "mall_codes": [
      "MALL_A0A47F3A"
    ]
  },
  {
    "area_id": 6,
    "area_name": "556国道商圈",
    "description": "位于556国道沿线的商业区域，服务周边社区",
    "mall_codes": [
      "MALL_D75029F8"
    ]
  }
]