[
  {
    "area_id": 1,
    "area_name": "静海老城商圈",
    "description": "以静海镇东方红路为核心的传统商业集聚区，集中了佳荣商厦、好润来商厦、银桥商场、龙海商场等本地老牌商业设施，是静海城区历史最悠久的商业中心。",
    "mall_codes": [
      "MALL_363126D1",
      "MALL_7C1515C5",
      "MALL_A3E50565",
      "MALL_B564C1CC",
      "MALL_8A4AE7A0",
      "MALL_4C5D4A32",
      "MALL_6A9DCB20",
      "MALL_566DD4ED",
      "MALL_18AD7B75",
      "MALL_8B48DC8D"
    ]
  },
  {
    "area_id": 2,
    "area_name": "新湖·朝阳道商圈",
    "description": "位于静海城区北部朝阳道与北华路交汇区域，以新湖广场为核心，聚集了新湖生活广场、新湖义乌商贸城、津海商城等多个商业项目，形成新兴的组团式商业带。",
    "mall_codes": [
      "MALL_359C77F0",
      "MALL_28EAC9BC",
      "MALL_E6490170",
      "MALL_90B470E4"
    ]
  },
  {
    "area_id": 3,
    "area_name": "团泊健康城商圈",
    "description": "位于团泊大道沿线的团泊新城片区，依托天津团泊健康城开发，布局有乐动港等商业配套，服务于康养、体育及文旅功能，属远郊特色功能型商圈。",
    "mall_codes": [
      "MALL_A63161AB"
    ]
  },
  {
    "area_id": 4,
    "area_name": "西外环潜力商圈",
    "description": "位于静海城区西部外围，包括阳光商业广场等小型商业点，分布较分散，目前商业成熟度较低，属待发展区域。",
    "mall_codes": [
      "MALL_B2F9E112"
    ]
  },
  {
    "area_id": 5,
    "area_name": "南部乡镇商圈",
    "description": "分布于静海区南部乡镇地带，如中旺镇、唐官屯等地，包含静海百货公司、西华购物中心、新世纪烟酒副食超市等服务本地居民的小型商业体，辐射范围有限。",
    "mall_codes": [
      "MALL_72BD6108",
      "MALL_419505D4",
      "MALL_9D0F0991"
    ]
  },
  {
    "area_id": 6,
    "area_name": "城区西南待建商圈",
    "description": "位于静海城区西南方向，目前仅有万达广场处于建设中阶段，尚未开业，未来可能带动周边形成新的商业中心。",
    "mall_codes": [
      "MALL_C06E465E"
    ]
  },
  {
    "area_id": 7,
    "area_name": "大邱庄及北部边缘商圈",
    "description": "位于静海北部远端，仅包含王中王购物中心，地处京福公路沿线，服务特定城镇节点，远离主城区，独立性强。",
    "mall_codes": [
      "MALL_A88E99BF"
    ]
  }
]