[
  {
    "area_id": 1,
    "area_name": "北城新区商圈",
    "description": "位于长丰县南部，以阜阳北路为轴线，聚集万达广场、金大地·庐州天地等核心商业项目，是北城新兴的城市级商业中心。",
    "mall_codes": [
      "MALL_2F570EA1",
      "MALL_B38D2E86",
      "MALL_4F7DD1EA"
    ]
  },
  {
    "area_id": 2,
    "area_name": "双墩镇商圈",
    "description": "覆盖双墩镇及周边区域，包含在建的丰迪广场，处于新城大道发展轴上，未来将成为北部重要商业节点。",
    "mall_codes": [
      "MALL_22494632"
    ]
  },
  {
    "area_id": 3,
    "area_name": "水湖镇商圈",
    "description": "位于长丰县中南部水湖镇片区，涵盖丰湖商城、外贸商店等本地生活型商业设施，服务县域南部居民。",
    "mall_codes": [
      "MALL_12D6F1F7",
      "MALL_7DDAB692"
    ]
  },
  {
    "area_id": 4,
    "area_name": "岗集-吴山沿线商圈",
    "description": "地处206国道沿线，以盛世购物广场为代表，服务于岗集、吴山等乡镇的区域性消费群体，具有较强交通导向特征。",
    "mall_codes": [
      "MALL_96B861A9"
    ]
  }
]