[
  {
    "area_id": 1,
    "area_name": "城东新区商圈",
    "description": "位于无为市东部新城区，以凤河路为核心，涵盖安德利旭辉广场和金世纪广场，是近年来发展较快的新兴商业集聚区。",
    "mall_codes": [
      "MALL_EE85BEBC",
      "MALL_F433AEB8"
    ]
  },
  {
    "area_id": 2,
    "area_name": "老城中心商圈",
    "description": "覆盖无为老城区核心地段，集中于西大街、十字街及周边区域，包括中瑞CBD购物中心、新百商厦、无为商之都等多个传统商业节点，是城市历史最悠久的商业中心。",
    "mall_codes": [
      "MALL_DB2AEFDB",
      "MALL_C9730A7C",
      "MALL_7CC03060",
      "MALL_FE5263F9",
      "MALL_317BEDF5",
      "MALL_BF9FF0DF"
    ]
  },
  {
    "area_id": 3,
    "area_name": "高新大道商圈",
    "description": "位于城市南部的高新产业带附近，依托高新大道与龙庵东路交叉口的交通优势，布局有新时代广场等商业设施，服务本地居民与产业园区人群。",
    "mall_codes": [
      "MALL_815140B3",
      "MALL_AED8968D"
    ]
  },
  {
    "area_id": 4,
    "area_name": "开城片区商圈",
    "description": "地处无为市西北部开城镇，以东领商城为代表，服务于乡镇居民的基础商业需求，属于区域性镇级商业中心。",
    "mall_codes": [
      "MALL_8DA982E3"
    ]
  },
  {
    "area_id": 5,
    "area_name": "西南商贸片区",
    "description": "位于主城区西南方向，靠近纵四路与红星美凯龙无为商场，包含无为长江路商场，形成以家居建材和专业市场为主的商贸功能区。",
    "mall_codes": [
      "MALL_22806341"
    ]
  },
  {
    "area_id": 6,
    "area_name": "石涧-瓦屋谭片区",
    "description": "位于无为市西部偏远乡镇区域，迎春超市购物中心为当地村级或乡镇级基础零售服务点，辐射范围有限。",
    "mall_codes": [
      "MALL_2396BE41"
    ]
  }
]