[
  {
    "area_id": 1,
    "area_name": "谢家集核心商圈",
    "description": "以卧龙山路与蔡新南路交汇区域为中心，聚集了人民商场、淮南·白马商业广场和熙城购物公园，是谢家集区传统商业最集中的地段，交通便利，人流密集，构成该区核心商业板块。",
    "mall_codes": [
      "MALL_16B1F0C2",
      "MALL_D6BA636C",
      "MALL_244D2965"
    ]
  },
  {
    "area_id": 2,
    "area_name": "蔡家岗商圈",
    "description": "位于谢家集区北部的蔡家岗片区，以花溪商城为代表，服务周边成熟居住区，配套较为完善，是区域性的社区型商业中心。",
    "mall_codes": [
      "MALL_69AD050F"
    ]
  },
  {
    "area_id": 3,
    "area_name": "春申大街商圈",
    "description": "依托春申大街发展起来的新兴商业节点，鸿朗休闲生活广场坐落于主干道交口，毗邻淮南五中，具备一定教育客流基础，定位为综合型街区式商业。",
    "mall_codes": [
      "MALL_CB8B9576"
    ]
  }
]