[
  {
    "area_id": 1,
    "area_name": "老城中心商圈",
    "description": "位于颍上县老城区核心地带，以解放路、人民路为主轴，聚集多个传统商贸场所，是县城历史最悠久的商业集中区。",
    "mall_codes": [
      "MALL_69A099F5",
      "MALL_5A81CFDB",
      "MALL_C6F92704",
      "MALL_441502BC",
      "MALL_79EAF929",
      "MALL_199BA689",
      "MALL_A279037F",
      "MALL_B3586B18"
    ]
  },
  {
    "area_id": 2,
    "area_name": "新城东片区商圈",
    "description": "位于颍上县东部新城区，依托吾悦广场等新兴商业项目形成的城市拓展型商圈，辐射周边新建住宅区和乡镇。",
    "mall_codes": [
      "MALL_372D836B",
      "MALL_50CA8AFA",
      "MALL_18F186F4"
    ]
  },
  {
    "area_id": 3,
    "area_name": "西南城镇群商圈",
    "description": "分布于县城西南方向多个重点镇区，涵盖南照镇、四十铺等区域性商业节点，服务本地乡镇居民。",
    "mall_codes": [
      "MALL_C5921FE0",
      "MALL_93770456"
    ]
  },
  {
    "area_id": 4,
    "area_name": "北部产业配套商圈",
    "description": "位于县城北部及外围工业或农业产业带附近，主要服务于矿区、乡镇居民的日常生活消费，具有较强社区属性。",
    "mall_codes": [
      "MALL_889ACFD1",
      "MALL_2B00002E",
      "MALL_93A6E98E",
      "MALL_C82C416D",
      "MALL_81E3333E",
      "MALL_5560C89C"
    ]
  }
]