[
  {
    "area_id": 1,
    "area_name": "兴宁市中心商圈",
    "description": "以兴宁市城区核心区域为主，涵盖人民大道、新兴大道及周边主要商业节点，集中了兴一广场、岁宝百货等较具规模的商业设施，是兴宁市传统且活跃的商业中心。",
    "mall_codes": [
      "MALL_70B3B38C",
      "MALL_B9366CC7",
      "MALL_93EF6C67"
    ]
  },
  {
    "area_id": 2,
    "area_name": "兴宁·毅德城商圈",
    "description": "位于兴南大道与兴宁大道交汇区域，以兴宁·毅德城为核心，包含其多个交易广场，形成以专业市场和批发零售为主的大型商贸集聚区，虽品牌密度较低，但整体体量大，是兴宁市重要的现代商贸平台。",
    "mall_codes": [
      "MALL_BCEF8DD1",
      "MALL_8F702A41",
      "MALL_2AD9972C"
    ]
  },
  {
    "area_id": 3,
    "area_name": "兴宁南部新城商圈",
    "description": "位于兴宁市南部新城发展轴，依托兴南大道沿线布局，涵盖凤凰商业广场等新兴商业节点，处于城市扩展方向，具备一定发展潜力，目前商业活跃度尚在培育阶段。",
    "mall_codes": [
      "MALL_7F9EE0B6"
    ]
  },
  {
    "area_id": 4,
    "area_name": "水口镇商圈",
    "description": "位于兴宁市下辖水口镇，以上斗八商场为代表，服务于本地乡镇居民，属于典型的乡镇级商业点，规模较小，品牌覆盖有限。",
    "mall_codes": [
      "MALL_2E8C3B52"
    ]
  },
  {
    "area_id": 5,
    "area_name": "罗岗镇商圈",
    "description": "位于兴宁市罗岗镇中心区域，以丹妞百货为主要商业载体，服务范围局限于镇域内，属基层乡镇商业形态，配套设施较为基础。",
    "mall_codes": [
      "MALL_8D7E334C"
    ]
  },
  {
    "area_id": 6,
    "area_name": "新圩镇商圈",
    "description": "位于兴宁市新圩镇，以友谊购物中心为典型代表，地处乡镇主干道旁，毗邻医院等公共设施，主要满足本地居民日常消费需求，商业层级较低。",
    "mall_codes": [
      "MALL_491FC66B"
    ]
  }
]