[
  {
    "area_id": 1,
    "area_name": "平山街道商圈",
    "description": "位于惠东县平山街道核心区域，涵盖惠东大道、新平大道沿线多个商业项目，是县城传统商业中心，聚集万隆商业中心、惠东天虹购物中心、美多购物中心等主要商场。",
    "mall_codes": [
      "MALL_D3B285B3",
      "MALL_D137BEE6",
      "MALL_F445C3C4",
      "MALL_377BE2D4",
      "MALL_6D4F6931",
      "MALL_EA0AED32",
      "MALL_79A281A4"
    ]
  },
  {
    "area_id": 2,
    "area_name": "华侨城商圈",
    "description": "依托华侨城大道沿线开发形成的新兴商业集聚区，以惠东天虹购物中心为核心，周边配套有丽江东岸广场等商业设施，服务华侨城及周边居住区。",
    "mall_codes": [
      "MALL_D137BEE6",
      "MALL_79A281A4"
    ]
  },
  {
    "area_id": 3,
    "area_name": "黄埠镇商圈",
    "description": "位于惠东县黄埠镇中心区域，集中分布海滨城、大汇城购物广场、安泰商业广场等多个商场，是黄埠镇最主要的商业集聚区，服务于本地居民及鞋业产业人群。",
    "mall_codes": [
      "MALL_C2C7D47D",
      "MALL_AC37160B",
      "MALL_F4485385",
      "MALL_A5211A2D",
      "MALL_5D03FEBB",
      "MALL_391973C7",
      "MALL_2F3778ED"
    ]
  },
  {
    "area_id": 4,
    "area_name": "白花镇商圈",
    "description": "位于惠东县白花镇新平大道沿线，以天盛广场为核心商业载体，服务白花镇及周边乡镇居民，属于区域性镇级商业中心。",
    "mall_codes": [
      "MALL_46E13273"
    ]
  },
  {
    "area_id": 5,
    "area_name": "环城南路商圈",
    "description": "位于平山街道南部环城南路与泰明路交汇区域，以欧洲城生活广场为主要商业节点，辐射周边住宅区，形成次级商业中心。",
    "mall_codes": [
      "MALL_79A9BC12"
    ]
  }
]