[
  {
    "area_id": 1,
    "area_name": "五星商圈",
    "description": "位于柳州市城中区核心地段，以中山中路和龙城路交汇处为中心，聚集了五星百货、梦之岛百货、999商城、二轻商场、工贸商场、地王商业广场等多个传统百货与商业体，是柳州历史最悠久、人流最密集的商业中心之一。",
    "mall_codes": [
      "MALL_48D71628",
      "MALL_CA7A3E70",
      "MALL_CD3EC5D1",
      "MALL_D0573ABE",
      "MALL_E8722E48",
      "MALL_A04F594E",
      "MALL_0DBCDA8F",
      "MALL_BF632D04",
      "MALL_47551A52",
      "MALL_A712B443"
    ]
  },
  {
    "area_id": 2,
    "area_name": "东环万达商圈",
    "description": "以东环大道256号万达广场为核心，辐射周边康顺路一带，包含万达广场及‘万达广场商圈’这一命名实体，是城中区东部较具规模的现代化商业集聚区，集购物、餐饮、娱乐于一体。",
    "mall_codes": [
      "MALL_D9FE5688",
      "MALL_9E05E29C"
    ]
  },
  {
    "area_id": 3,
    "area_name": "河东新区商圈",
    "description": "位于柳州市城中区河东片区，涵盖桂中大道与文昌路沿线，包括柳州红星新天地、阳光百城市广场、五星百货·乐和城以及建设中的秀品天地等项目，是近年来重点发展的新兴城市商业中心，定位中高端，配套完善。",
    "mall_codes": [
      "MALL_AC0A35AD",
      "MALL_A04F594E",
      "MALL_F41D5C4F",
      "MALL_7B518279"
    ]
  },
  {
    "area_id": 4,
    "area_name": "沿江文旅商圈",
    "description": "依托沿江路滨江区位，以双渔汇为代表，靠近柳江景观带，具备一定文旅休闲属性，是城中区北部沿江商业节点。",
    "mall_codes": [
      "MALL_CF2F9217"
    ]
  },
  {
    "area_id": 5,
    "area_name": "金鱼巷-花旗商圈",
    "description": "位于金鱼巷与龙城路交界区域，以东都百货所在花旗壹号楼为核心，临近五星商圈但具有独立社区型商业特征，体量较小但地理位置优越。",
    "mall_codes": [
      "MALL_125C45D1"
    ]
  }
]