[
  {
    "area_id": 1,
    "area_name": "新安县城中心商圈",
    "description": "位于新安县城核心区域，涵盖汉关大道、涧慕大街及上海路周边，集中了供一销商厦、河南省新安县供销商厦、百货大楼和大张盛德美购物广场等主要商业设施，是县城传统商业中心。",
    "mall_codes": [
      "MALL_BED3BB59",
      "MALL_64DA0F9A",
      "MALL_0354B482",
      "MALL_DD95A571"
    ]
  },
  {
    "area_id": 2,
    "area_name": "五头镇社区商圈",
    "description": "服务于五头镇本地居民，以新世纪超市为核心，位于仓上村五头一中对面，属于乡镇级生活配套商业节点。",
    "mall_codes": [
      "MALL_C67205A4"
    ]
  },
  {
    "area_id": 3,
    "area_name": "城北新兴居住区商圈",
    "description": "位于新安县城北部金斗路沿线，依托群泰购物服务盛世和苑等新建住宅区，属于城市扩展形成的次级生活商圈。",
    "mall_codes": [
      "MALL_B199359B"
    ]
  },
  {
    "area_id": 4,
    "area_name": "铁门镇外围产业带商圈",
    "description": "位于新安县铁门镇方向的新仓大道沿线，以金三角供销购物广场为代表，地处城乡结合部或产业园区周边，服务范围偏重区域性基础消费。",
    "mall_codes": [
      "MALL_A0C49B6C"
    ]
  }
]