[
  {
    "area_id": 1,
    "area_name": "围场镇中心商圈",
    "description": "位于围场满族蒙古族自治县围场镇核心区域，集中分布于木兰中路与伊逊路、通祥街交汇地带，涵盖北雁商城、供销商城、新木兰商城、美神购物中心等多个商业载体，是县城传统商业中心。",
    "mall_codes": [
      "MALL_E3CC86BD",
      "MALL_B940F618",
      "MALL_833FC48B",
      "MALL_CEEE2C6B",
      "MALL_E4E73850",
      "MALL_E4693EF2",
      "MALL_0F33D162",
      "MALL_A39C714F",
      "MALL_A7463CF0"
    ]
  },
  {
    "area_id": 2,
    "area_name": "大头山乡商圈",
    "description": "位于围场县大头山乡大头山村，以太和商城为代表，服务当地乡村居民，商业规模较小，辐射范围有限。",
    "mall_codes": [
      "MALL_A37F664A"
    ]
  },
  {
    "area_id": 3,
    "area_name": "城东永合路商圈",
    "description": "位于围场镇东部永合路沿线，包含时利和购物中心与永达商城，形成区域性小型商业聚集区，主要服务于周边社区。",
    "mall_codes": [
      "MALL_E40EE5D1",
      "MALL_3C26573A"
    ]
  }
]