[
  {
    "area_id": 1,
    "area_name": "中山东路核心商圈",
    "description": "沿中山东路主干道分布，集中了勒泰中心、北国先天下、乐汇城等主要商业体，地铁站点密集，是长安区传统商业中心。",
    "mall_codes": [
      "MALL_403A9CD5",
      "MALL_AA2EB25B",
      "MALL_EA3CE93F",
      "MALL_B4A8733F",
      "MALL_DCF9189B",
      "MALL_71024238",
      "MALL_8B312DFD",
      "MALL_FBE2F5CB",
      "MALL_2FE0ECDE"
    ]
  },
  {
    "area_id": 2,
    "area_name": "万达广场商圈",
    "description": "以万达广场为核心，位于中山东路东段，周边有北国商城益庄购物中心和港悦广场，形成东部新兴商业集聚区。",
    "mall_codes": [
      "MALL_18414117",
      "MALL_B3C8A031",
      "MALL_2FE0ECDE"
    ]
  },
  {
    "area_id": 3,
    "area_name": "胜利北大街商圈",
    "description": "位于胜利北大街沿线，包括美博城电商直播基地、鑫利广场和天河通信广场，以专业市场和区域性商业为主。",
    "mall_codes": [
      "MALL_B249BEC7",
      "MALL_8D07C4E2",
      "MALL_EFF8CE8E"
    ]
  },
  {
    "area_id": 4,
    "area_name": "新客站/南三条商圈",
    "description": "靠近老南三条批发市场区域，涵盖聚缘城、金正玩具城等小型专业市场，具有批发零售混合特征。",
    "mall_codes": [
      "MALL_D10A2664",
      "MALL_9DEEA0A7"
    ]
  },
  {
    "area_id": 5,
    "area_name": "丰收路商圈",
    "description": "位于北部丰收路与百花街交口，以北城国际亲子广场为代表，服务周边居住区的社区型商业中心。",
    "mall_codes": [
      "MALL_58F1402D"
    ]
  },
  {
    "area_id": 6,
    "area_name": "博物院商圈",
    "description": "围绕博物院地铁站形成的高端商业节点，东尚年轻力中心位于此，毗邻中山东路核心段但定位差异化。",
    "mall_codes": [
      "MALL_1ED5F617"
    ]
  }
]