[
  {
    "area_id": 1,
    "area_name": "万地广场商圈",
    "description": "以丽水万地广场为核心，位于花园路沿线，是莲都区北部较为集中的商业节点，周边聚集部分社区型商业配套。",
    "mall_codes": [
      "MALL_93DA5590"
    ]
  },
  {
    "area_id": 2,
    "area_name": "银泰城商圈",
    "description": "围绕丽水银泰城形成的城市级商业中心，地处花园路与卢镗街交叉口，交通便利，辐射范围广，是莲都区南部主要消费聚集区。",
    "mall_codes": [
      "MALL_4A4C165F"
    ]
  },
  {
    "area_id": 3,
    "area_name": "老城区中心商圈",
    "description": "涵盖处州大道以北、丽阳街至解放街一带的老城核心商业带，集中了星火商城、金马时代广场、金汇广场等多个传统商场和市场，商业密度高。",
    "mall_codes": [
      "MALL_E3C695F4",
      "MALL_1D4733E3",
      "MALL_2A05E82B",
      "MALL_34D31508",
      "MALL_2E367039",
      "MALL_ABB8816F",
      "MALL_E4F77ECC",
      "MALL_AF79590F",
      "MALL_FE04147A"
    ]
  },
  {
    "area_id": 4,
    "area_name": "南城产业区商圈",
    "description": "位于莲都区南部工业与居住融合区域，以未来城为综合载体，结合南锦购物中心、南城商贸中心等，服务本地居民及产业园区人群。",
    "mall_codes": [
      "MALL_C52E289B",
      "MALL_194FA90D",
      "MALL_0A3E0B8B",
      "MALL_ACDA00C3",
      "MALL_89E9F8BF",
      "MALL_5CEF4B14"
    ]
  },
  {
    "area_id": 5,
    "area_name": "信息产业园商圈",
    "description": "依托绿谷信息产业园形成的新兴商业节点，目前仅有MT新嬉里超市布局，主要服务于园区内部办公人群。",
    "mall_codes": [
      "MALL_F8D28C03"
    ]
  },
  {
    "area_id": 6,
    "area_name": "联城路外围商圈",
    "description": "位于莲都区西北部边缘地带，以龙贸国际商业广场为代表，处于联平路与联城路交叉口附近，属区域性配套商业。",
    "mall_codes": [
      "MALL_BB601F68"
    ]
  },
  {
    "area_id": 7,
    "area_name": "锦侨奥特莱斯商圈",
    "description": "位于处州大道西侧的特色零售商业点，以锦侨奥特莱斯广场为主导，定位为折扣购物场所，独立于主城商业集群。",
    "mall_codes": [
      "MALL_006628E1"
    ]
  },
  {
    "area_id": 8,
    "area_name": "丽水大厦商城商圈",
    "description": "位于城市中部偏东的单体商场节点，丽水大厦商城独立成点，周边暂无其他大型商业体协同，形成微型商业单元。",
    "mall_codes": [
      "MALL_E3C695F4"
    ]
  }
]