[
  {
    "area_id": 1,
    "area_name": "回龙路商圈",
    "description": "以回龙路为核心轴线，聚集多个地下商城及商业广场，包括中昊地下商城、华翔广场、步步高广场等，是永定区传统人流密集的商业中心区域。",
    "mall_codes": [
      "MALL_37A09BE8",
      "MALL_313E304D",
      "MALL_3E8748D5",
      "MALL_422D556B",
      "MALL_2CE7A19B",
      "MALL_4A112A9B"
    ]
  },
  {
    "area_id": 2,
    "area_name": "解放路文昌阁商圈",
    "description": "位于解放路与文昌阁交汇地带，涵盖灯火文昌购物广场、星悦茂、梅尼购物中心（解放路）等多个集中商业体，构成永定城区核心零售与步行街消费区。",
    "mall_codes": [
      "MALL_C7665528",
      "MALL_E3A7632D",
      "MALL_02D9C559",
      "MALL_FAF51A04",
      "MALL_4281843B"
    ]
  },
  {
    "area_id": 3,
    "area_name": "人民路商圈",
    "description": "依托人民路主干道形成的商业集聚区，包含影苑商城和永定街道地下商城，邻近政务与居民生活核心区，具备较强日常消费基础。",
    "mall_codes": [
      "MALL_DB758A7C",
      "MALL_4281843B"
    ]
  },
  {
    "area_id": 4,
    "area_name": "官黎坪/迎宾路商圈",
    "description": "位于城市南部入口区域，覆盖张家界国际旅游商业城和竹园里商业城，紧邻汽车站与交通干道，服务于外来游客及区域商贸流通。",
    "mall_codes": [
      "MALL_952BCD7F",
      "MALL_E6722959"
    ]
  },
  {
    "area_id": 5,
    "area_name": "澧水河北岸商圈",
    "description": "分布于澧水河沿岸北部片区，包括澧水广场和裕美和购物中心，地理位置偏北，服务周边大型居住区，具有社区型商业特征。",
    "mall_codes": [
      "MALL_982CE8D5",
      "MALL_1C9E8864"
    ]
  },
  {
    "area_id": 6,
    "area_name": "大庸路商圈",
    "description": "位于大庸路沿线，以天门中心广场为代表，虽当前部分处于装修状态，但地处城市主干道，具备未来发展潜力，为城区西部重要节点。",
    "mall_codes": [
      "MALL_7691C64D"
    ]
  },
  {
    "area_id": 7,
    "area_name": "永定大道商圈",
    "description": "坐落于永定大道与兑泽路交汇处，以张家界梅尼购物公园为核心，辐射周边新兴住宅与城市拓展区域，属城区东部主要商业支点。",
    "mall_codes": [
      "MALL_0278186A"
    ]
  },
  {
    "area_id": 8,
    "area_name": "田家台路商圈",
    "description": "位于田家台路与沿江路交叉口附近，以义乌商贸城为代表，侧重小商品批发与区域性专业市场功能，具有明显的物流集散特征。",
    "mall_codes": [
      "MALL_CB76D493"
    ]
  }
]