[
  {
    "area_id": 1,
    "area_name": "泽当大道商圈",
    "description": "位于乃东区核心主干道泽当大道沿线，涵盖火车站对面及湖北大道交叉口附近的商业项目，是山南市人口和交通较为集中的区域，具备区域级商业辐射能力。",
    "mall_codes": [
      "MALL_A34C0E43",
      "MALL_F85D5E79"
    ]
  },
  {
    "area_id": 2,
    "area_name": "湖南路商圈",
    "description": "以湖南路与安徽大道交叉区域为核心，覆盖百润购物中心，地处城市主要道路交汇处，具有较好的可达性和区域服务功能。",
    "mall_codes": [
      "MALL_3C035C13"
    ]
  },
  {
    "area_id": 3,
    "area_name": "格桑路商圈",
    "description": "沿格桑路分布，连接雅砻商业广场与鸿吉商业广场，形成东西向的街区式商业集聚带，服务于周边密集居住区。",
    "mall_codes": [
      "MALL_7DDE454C",
      "MALL_C7D2A7BB"
    ]
  }
]