[
  {
    "area_id": 1,
    "area_name": "平坝老城商圈",
    "description": "位于平坝区中心城区，覆盖中山南路、黎阳路及周边核心道路交叉区域，是区内传统商业集聚地，包含东风大厦商城、丽钦商贸城、绿谷购物中心(西门坡批发兼零售)等商场。",
    "mall_codes": [
      "MALL_EFFB1510",
      "MALL_1310D686",
      "MALL_E4E75A23"
    ]
  },
  {
    "area_id": 2,
    "area_name": "贵黄公路沿线商圈",
    "description": "沿贵黄公路分布的新兴商业带，依托交通主干道和高速出入口形成，涵盖樱花假日广场、益田·樱花十里等项目，具备一定城市门户特征。",
    "mall_codes": [
      "MALL_C9DDCE30",
      "MALL_D74BADA7"
    ]
  },
  {
    "area_id": 3,
    "area_name": "马场镇商圈",
    "description": "位于平坝区马场镇区域，服务本地居民为主的区域性商业节点，以林城购物中心为代表。",
    "mall_codes": [
      "MALL_9E9F7D87"
    ]
  },
  {
    "area_id": 4,
    "area_name": "高峰镇商圈",
    "description": "覆盖平坝南部甘凯线沿线乡镇商业点，以胜文购物中心为核心，服务于高峰中学及周边乡镇居民。",
    "mall_codes": [
      "MALL_27087FB9"
    ]
  },
  {
    "area_id": 5,
    "area_name": "夏云工业园商圈",
    "description": "位于平坝北部工业与城镇结合区域，包含家家乐购物中心、平坝区心连心购物中心等分散布点，主要满足基础生活消费。",
    "mall_codes": [
      "MALL_A8450D81",
      "MALL_69F15841"
    ]
  },
  {
    "area_id": 6,
    "area_name": "十字乡外围商圈",
    "description": "地处平坝区偏远乡镇地带，绿谷购物中心（县道与乡道交叉口）代表边缘区域的基础零售布局。",
    "mall_codes": [
      "MALL_6C549358"
    ]
  },
  {
    "area_id": 7,
    "area_name": "屯堡国际新城商圈",
    "description": "依托贵安新区辐射发展的新型城镇商业节点，以屯堡商贸城为标志，处于城市拓展方向上的潜力区域。",
    "mall_codes": [
      "MALL_0A042F0D"
    ]
  },
  {
    "area_id": 8,
    "area_name": "城北乡镇商圈",
    "description": "位于平坝西北部偏远县域道路沿线，以顺丰购物中心为代表，服务于零散乡村聚居区的基础购物需求。",
    "mall_codes": [
      "MALL_5CACC6D5"
    ]
  },
  {
    "area_id": 9,
    "area_name": "城东新区商圈",
    "description": "位于平坝城区东部发展轴线，FUN天地坐落于此，虽当前数据为空，但地理位置具有未来开发潜力。",
    "mall_codes": [
      "MALL_B107E236"
    ]
  }
]