[
  {
    "area_id": 1,
    "area_name": "璧城老城区商圈",
    "description": "以璧城街道为核心的传统商业集聚区，涵盖解放路、文星路等主干道沿线的多个老牌商场和购物中心，是璧山区历史最悠久的商业中心。",
    "mall_codes": [
      "MALL_62B990FC",
      "MALL_EE559DA3",
      "MALL_7E030421",
      "MALL_72555367"
    ]
  },
  {
    "area_id": 2,
    "area_name": "璧泉砂之船奥莱商圈",
    "description": "位于璧泉街道白羊路，以砂之船(璧山)奥特莱斯为核心，集中布局高端折扣零售商业，是璧山区最具规模的现代化大型商业综合体集群。",
    "mall_codes": [
      "MALL_9E2B78C7",
      "MALL_A2248188",
      "MALL_8D2CF7D2"
    ]
  },
  {
    "area_id": 3,
    "area_name": "金剑路-东林大道商圈",
    "description": "覆盖金剑路与东林大道交叉区域，包含摩登时代广场及新世纪百货等项目，处于城市主干道交汇处，具备较强交通辐射能力，是连接老城与新区的重要商业节点。",
    "mall_codes": [
      "MALL_761058A8",
      "MALL_92E82D1B"
    ]
  },
  {
    "area_id": 4,
    "area_name": "铜山路滨江商圈",
    "description": "位于铜山路与沿河西路南段周边，依托璧山新天地项目形成滨水商业带，毗邻河道景观，定位为集休闲、购物于一体的新兴城市生活配套区域。",
    "mall_codes": [
      "MALL_8545AA59"
    ]
  },
  {
    "area_id": 5,
    "area_name": "秀湖金科SKY MALL商圈",
    "description": "以泉山路金科秀湖天都SKY MALL为核心，服务于秀湖板块高端住宅区，主打社区型商业服务，具有较强的居住配套属性。",
    "mall_codes": [
      "MALL_4F1FFA60"
    ]
  }
]