[
  {
    "area_id": 1,
    "area_name": "向阳路商圈",
    "description": "以向阳路为核心的传统商业集聚区，集中了新世纪百货、协信广场及多个老牌商场，是长寿城区老城中心的主要消费场所。",
    "mall_codes": [
      "MALL_38DB6264",
      "MALL_52E6F4E8",
      "MALL_DB8A6B6B",
      "MALL_27201E19",
      "MALL_67CA46B8",
      "MALL_B4483E8C"
    ]
  },
  {
    "area_id": 2,
    "area_name": "桃源大道商圈",
    "description": "位于桃源大道沿线的新兴商业带，以凯谊世纪广场及其附属建筑为主，形成区域性商业节点。",
    "mall_codes": [
      "MALL_C0405AC8",
      "MALL_EAFA51D6"
    ]
  },
  {
    "area_id": 3,
    "area_name": "凤城桃花大道商圈",
    "description": "位于凤城街道桃花大道的商业聚集点，以东方水岸商业广场为代表，服务周边居住区。",
    "mall_codes": [
      "MALL_43DFC589"
    ]
  },
  {
    "area_id": 4,
    "area_name": "经开路-建新东路商圈",
    "description": "分布于经开路与建新东路附近的商业设施群，包括城中城广场和好友来购物中心，服务于城市扩展区域。",
    "mall_codes": [
      "MALL_78ACB41C",
      "MALL_D8E964BE"
    ]
  },
  {
    "area_id": 5,
    "area_name": "长寿北站商圈",
    "description": "依托长寿北站规划建设的新兴商业区域，目前以在建的爱琴海购物中心为标志，未来有望成为区域级商业中心。",
    "mall_codes": [
      "MALL_8D1EE2EE"
    ]
  },
  {
    "area_id": 6,
    "area_name": "海棠西街商圈",
    "description": "位于海棠西街附近的独立商业点，以金鑫购物中心为代表，服务南部较远城区。",
    "mall_codes": [
      "MALL_2AF67FA1"
    ]
  }
]