[
  {
    "area_id": 1,
    "area_name": "奉节老城中心商圈",
    "description": "以夔州路、诗城路为核心的传统商业集聚区，集中了国平商业广场、地王商场、佳铃百货等本地主要商场，覆盖永安镇核心消费人群。",
    "mall_codes": [
      "MALL_B5DBBA51",
      "MALL_F0D738AA",
      "MALL_BF0DE8E4",
      "MALL_E24FDE96",
      "MALL_17630AF3",
      "MALL_40EC5F8E",
      "MALL_A60559A0",
      "MALL_FDE4923A",
      "MALL_413670ED"
    ]
  },
  {
    "area_id": 2,
    "area_name": "奉节商都/海成路商圈",
    "description": "依托奉节商都及新世纪百货形成的区域级商业节点，位于海成路沿线，服务周边密集居住区，具有较强的生活配套功能。",
    "mall_codes": [
      "MALL_40EC5F8E",
      "MALL_A60559A0"
    ]
  },
  {
    "area_id": 3,
    "area_name": "鱼复新城商圈",
    "description": "位于鱼复街道人和街人民广场周边，布局新世纪超市等基础商业设施，服务于新兴城区居民，属次级生活型商圈。",
    "mall_codes": [
      "MALL_03AD9050"
    ]
  },
  {
    "area_id": 4,
    "area_name": "环彬商圈",
    "description": "以环彬白帝时代广场为支点，分布于城市西部边缘的区域性商业点，辐射局部社区，规模较小但具备一定综合服务能力。",
    "mall_codes": [
      "MALL_0EF4C418"
    ]
  },
  {
    "area_id": 5,
    "area_name": "茶店-金鑫商贸城商圈",
    "description": "位于县城外围的江宜神舟老县城及英才街片区，由茶店商贸城与金鑫商贸城构成，主打批发零售与本地生活服务，属边缘型专业市场集聚区。",
    "mall_codes": [
      "MALL_A2C97D4B",
      "MALL_A564D2D3"
    ]
  },
  {
    "area_id": 6,
    "area_name": "兴星购物中心商圈",
    "description": "位于奉节南部廊桥街与乳峰路交叉口附近的独立商业点，孤立布局，服务特定乡镇或城乡结合部客群，属微型区域性商业中心。",
    "mall_codes": [
      "MALL_0DAD106C"
    ]
  },
  {
    "area_id": 7,
    "area_name": "万达广场商圈",
    "description": "位于夔州街道万胜路的已暂停营业万达广场所在区域，曾规划为城市级商业中心，目前处于停业状态，但仍具潜在地标意义。",
    "mall_codes": [
      "MALL_F7145821"
    ]
  }
]