[
  {
    "area_id": 1,
    "area_name": "哈西商圈",
    "description": "以万达广场、凯德广场·学府为核心，覆盖哈西地区的主要商业集聚区，包含周边多个商场，是南岗区西部的新兴商业中心。",
    "mall_codes": [
      "MALL_141639D8",
      "MALL_E31EF8EF",
      "MALL_2601BFFA",
      "MALL_3B0AC7AF",
      "MALL_D63787EC"
    ]
  },
  {
    "area_id": 2,
    "area_name": "学府路商圈",
    "description": "位于学府路沿线，以勇超商场、和兴商厦等为代表，服务高校密集区域的居民与学生群体，形成区域性商业带。",
    "mall_codes": [
      "MALL_13B3AFB0",
      "MALL_30CFB3F3",
      "MALL_F6B3E46B"
    ]
  },
  {
    "area_id": 3,
    "area_name": "博物馆/东大直街商圈",
    "description": "以地铁博物馆站为中心，沿东大直街分布松雷商业、远大购物中心、秋林公司等多个核心商场，是南岗区传统最繁华的商业核心区。",
    "mall_codes": [
      "MALL_BF22C843",
      "MALL_375C64A2",
      "MALL_C2630639",
      "MALL_902CC3BA",
      "MALL_AD4C1030",
      "MALL_94408BF7",
      "MALL_6CA65C4C",
      "MALL_92D04857",
      "MALL_F3600544"
    ]
  },
  {
    "area_id": 4,
    "area_name": "红旗大街商圈",
    "description": "位于红旗大街沿线，以红博中央公园、红博会展购物广场为核心，聚集艺汇家城市广场等商业体，构成南岗东部的重要商业组团。",
    "mall_codes": [
      "MALL_59C11EAB",
      "MALL_964E9B7A",
      "MALL_87494BE1"
    ]
  },
  {
    "area_id": 5,
    "area_name": "宣化街商圈",
    "description": "以新吉购物中心为代表，位于宣化街附近，商业密度相对较低，服务于周边居民区的区域性商业节点。",
    "mall_codes": [
      "MALL_93DAD553"
    ]
  }
]