[
  {
    "area_id": 1,
    "area_name": "庆安镇中心商圈",
    "description": "位于庆安镇核心区域，涵盖中央东大街与东商业街周边，聚集了华辰时代广场、同源商城、新世纪购物广场等多个主要商业体，是庆安县最繁华的商业集中区。",
    "mall_codes": [
      "MALL_44D88925",
      "MALL_DF892CB6",
      "MALL_A27533F0",
      "MALL_E57EF0B6",
      "MALL_48AFEB59",
      "MALL_50CA63EE"
    ]
  },
  {
    "area_id": 2,
    "area_name": "南部居住区商圈",
    "description": "位于庆安镇南部，以雅典购物中心为核心，服务于周边居民区，商业密度较低，定位为社区型消费场所。",
    "mall_codes": [
      "MALL_3DA14483"
    ]
  },
  {
    "area_id": 3,
    "area_name": "龙泉外围商圈",
    "description": "位于庆安县郊区，靠近县道与乡道交叉口，以龙泉购物中心为代表，地理位置偏远，服务范围覆盖周边乡镇，属于边缘型商业节点。",
    "mall_codes": [
      "MALL_CE4869F3"
    ]
  }
]